README.md
pyproject.toml
setup.py
cryptography-stubs/__about__.pyi
cryptography-stubs/__init__.pyi
cryptography-stubs/exceptions.pyi
cryptography-stubs/fernet.pyi
cryptography-stubs/utils.pyi
cryptography-stubs/hazmat/__init__.pyi
cryptography-stubs/hazmat/_der.pyi
cryptography-stubs/hazmat/_oid.pyi
cryptography-stubs/hazmat/_types.pyi
cryptography-stubs/hazmat/backends/__init__.pyi
cryptography-stubs/hazmat/backends/interfaces.pyi
cryptography-stubs/hazmat/backends/openssl/__init__.pyi
cryptography-stubs/hazmat/backends/openssl/aead.pyi
cryptography-stubs/hazmat/backends/openssl/backend.pyi
cryptography-stubs/hazmat/backends/openssl/ciphers.pyi
cryptography-stubs/hazmat/backends/openssl/cmac.pyi
cryptography-stubs/hazmat/backends/openssl/decode_asn1.pyi
cryptography-stubs/hazmat/backends/openssl/dh.pyi
cryptography-stubs/hazmat/backends/openssl/dsa.pyi
cryptography-stubs/hazmat/backends/openssl/ec.pyi
cryptography-stubs/hazmat/backends/openssl/ed25519.pyi
cryptography-stubs/hazmat/backends/openssl/ed448.pyi
cryptography-stubs/hazmat/backends/openssl/encode_asn1.pyi
cryptography-stubs/hazmat/backends/openssl/hashes.pyi
cryptography-stubs/hazmat/backends/openssl/hmac.pyi
cryptography-stubs/hazmat/backends/openssl/ocsp.pyi
cryptography-stubs/hazmat/backends/openssl/poly1305.pyi
cryptography-stubs/hazmat/backends/openssl/rsa.pyi
cryptography-stubs/hazmat/backends/openssl/utils.pyi
cryptography-stubs/hazmat/backends/openssl/x25519.pyi
cryptography-stubs/hazmat/backends/openssl/x448.pyi
cryptography-stubs/hazmat/backends/openssl/x509.pyi
cryptography-stubs/hazmat/bindings/__init__.pyi
cryptography-stubs/hazmat/bindings/openssl/__init__.pyi
cryptography-stubs/hazmat/bindings/openssl/_conditional.pyi
cryptography-stubs/hazmat/bindings/openssl/binding.pyi
cryptography-stubs/hazmat/primitives/__init__.pyi
cryptography-stubs/hazmat/primitives/_asymmetric.pyi
cryptography-stubs/hazmat/primitives/_cipheralgorithm.pyi
cryptography-stubs/hazmat/primitives/_serialization.pyi
cryptography_347_stubs.egg-info/PKG-INFO
cryptography_347_stubs.egg-info/SOURCES.txt
cryptography_347_stubs.egg-info/dependency_links.txt
cryptography_347_stubs.egg-info/top_level.txt