Metadata-Version: 2.1
Name: cryptography-347-stubs
Version: 1.0.0
Summary: Stubs for cryptography v3.4.7
Home-page: https://github.com/benesch/cryptography-347-stubs.git
Author: Nikhil Benesch
Author-email: nikhil.benesch@gmail.com
License: UNKNOWN
Platform: UNKNOWN
